{
	"intro-p" : [
		{
			"p-text" : "Portfolio"
		}
	],

	"intro-h1" : [
		{
			"h1-text" : "Of web developer"
		}
	],

	"nav-link" : [
		{
			"href" : "#header",
			"description" : "Home"
		},
		{
			"href" : "#about",
			"description" : "About me"
		},
		{
			"href" : "#skills",
			"description" : "Skills"
		},
		{
			"href" : "#my-works",
			"description" : "Works"
		},
		{
			"href" : "#contact",
			"description" : "Contacts"
		}
	],

	"lang-block" : [
		{
			"data" : "uk",
			"icon" : "lang__icon lang__icon_uk lang__icon_active",
			"country" : "USA"
		},
		{
			"data" : "ua",
			"icon" : "lang__icon lang__icon_ua",
			"country" : "UA"
		},
		{
			"data" : "ru",
			"icon" : "lang__icon lang__icon_ru",
			"country" : "RUS"
		}
	],

	"about-block" : [
		{
			"about-descr" : "About me",
			"info-title"  : "About myself",
			"info-text"   : "Hello everyone, my name is Roman. Recently I have been doing of web development. I do adaptive, cross browshing, dynamic websites with mobile first. This guarantees is a beautiful visualization and fast speed of website on all famous browsers. I prefer to write native code.  This site is no exception - HTML5, CSS3, JS, AJAX, BEM, Canvas. In my projects I use last web technologies,  which exist today. I constantly study and learn something new. I'am looking forward to working with you."
		}
	],

	"skills-block" : [
		{
			"skills-descr" : "My skills",
			"skills-li" : [
				{
					"skills-title" : "Higher education",
					"skills-text"  : "Graduated from economical faculty of DonNTU in 2007, have a Master's degree."
				},
				{
					"skills-title" : "Knowledge of Web",
					"skills-text"  : "I took  a course Front-end Deleloper. I'am looking through video of web , reading books, documentation, articles, forums. Now I learn advanced js and plan to study framework Angular. I use HTML5/CSS3, JS, methodology CSS-architecture BEM, preprocessor Sass, assemblers Webpack,Gulp and system of version control Git."
				}
			]
		}
	],

	"my-works-block" : [
		{
			"my-works-descr" : "My works",
			"gallery-blocks" : [
				{
					"gallery-class" : "block_k-full",
					"href" : "http://test.ifb.com.ua/"	
				},
				{
					"gallery-class" : "block_pension",
					"href" : "http://new.penscapital.com.ua/"	
				},
				{
					"gallery-class" : "block_green",
					"href" : ""	
				},
				{
					"gallery-class" : "block_summary",
					"href" : ""	
				},
				{
					"gallery-class" : "block_barberi",
					"href" : ""	
				}
			]
		}
	],

	"contact-block" : [
		{
			"contact-descr" : "Contact me",
			"address-blocks" : [
				{
					"i-class" : "fa fa-map-marker",
					"address-text" : "Ukraine Kiev"
				},

				{
					"i-class" : "fa fa-envelope",
					"address-text" : "roma.novomodnyi@gmail.com"
				},

				{
					"i-class" : "fa fa-mobile",
					"address-text" : "+38 (050) 927 38 57"
				}
			],

			"form-descr" : [
				{
					"form-title" : "Send a message"
				}
			],

			"form-input" : [
				{
					"field-descr" : "Your name",
					"field-id" : "label-name",
					"input-type" : "text",
					"field-error" : "Enter your name",
					"data-target" : "name",
					"placeholder" : "Your name",
					"data-id" : "name",
					"data-type" : "text"
				},

				{
					"field-descr" : "Your email",
					"field-id" : "label-email",
					"input-type" : "email",
					"field-error" : "Enter your mail",
					"data-target" : "email",
					"placeholder" : "Your mail",
					"data-id" : "email",
					"data-type" : "email"
				}
			],

			"text-area" : [
				{
					"area-descr" : "Your message",
					"area-placeholder" : "Your message...",
					"area-error" : "Enter your message",
					"data-id" : "message",
					"data-type" : "text"
				}
			],

			"form-submit" : [
				{
					"value" : "Send",
					"error" : "Your message Send"
				}
			]


		}
	],

	"footer" : [
		{
			"author" : "Novomodniy Roman",
			"copy" : "Copyright © 2018",
			"social-group" : [
				{
					"add-class" : "soc-elem__link_telegram",
					"icon-class" : "fab fa-telegram",
					"link-href" : "tg://resolve?domain=@romanovomodniy"
				},
				{
					"add-class" : "soc-elem__link_viber",
					"icon-class" : "fab fa-viber",
					"link-href" : "viber://add?number=380509273857"
				},
				{
					"add-class" : "soc-elem__link_linkedin",
					"icon-class" : "fab fa-linkedin",
					"link-href" : "https://www.linkedin.com/in/%D1%80%D0%BE%D0%BC%D0%B0-%D0%BD%D0%BE%D0%B2%D0%BE%D0%BC%D0%BE%D0%B4%D0%BD%D1%8B%D0%B9-1200b5139/"
				},
				{
					"add-class" : "soc-elem__link_github",
					"icon-class" : "fab fa-github",
					"link-href" : "https://github.com/RomaNovo"
				},
				{
					"add-class" : "soc-elem__link_skype",
					"icon-class" : "fab fa-skype",
					"link-href" : "skype:romaaaaa435"
				}
			]
		}
	]				
}